{
  "Mon": {
    "lunch": ["콩가루배추국, 제육볶음, 감자사라다, 시금치무침"],
    "dinner": ["참치김치국, 돈까스, 미니새송이볶음, 우엉조림"]
  },
  "Tue": {
    "lunch": ["고추장찌개, 고등어구이, 궁채볶음, 오이도라지무침"],
    "dinner": ["어묵국, 모듬햄볶음, 콩나물무침, 쑥갓나물무침"]
  },
  "Wed": {
    "lunch": ["근대국, 오징어까스, 계란말이, 꽈리고추어묵볶음"],
    "dinner": ["바지락무채국, 불고기, 청포묵김무침, 진미채볶음"]
  },
  "Thu": {
    "lunch": ["순두부찌개, 닭갈비, 고구마튀김, 참나물무침"],
    "dinner": ["감자수제비국, 고구마순나물, 두부조림, 메추리알조림"]
  },
  "Fri": {
    "lunch": ["콩나물국, 오징어야채무침, 잡채, 해초무침"],
    "dinner": ["된장찌개, 생선조림, 건파래볶음, 오리야채무침"]
  }
}
